ProbabilisticDiffusion/ProbabilisticDiffusion.py
ProbabilisticDiffusion/__init__.py
ProbabilisticDiffusion/utils.py
probabilisticdiffusion-2.0.1.dist-info/METADATA
probabilisticdiffusion-2.0.1.dist-info/WHEEL
probabilisticdiffusion-2.0.1.dist-info/top_level.txt
probabilisticdiffusion-2.0.1.dist-info/RECORD
