Metadata-Version: 2.4
Name: ProbabilisticDiffusion
Version: 2.0.1
Summary: A PyTorch implementation of De-noising Diffusion Probabilistic Models
Author-email: Kristof Pusztai <kpusztai@berkeley.edu>
Project-URL: Homepage, https://github.com/KristofPusztai/ProbabilisticDiffusion
Classifier: Programming Language :: Python :: 3
Classifier: License :: OSI Approved :: MIT License
Classifier: Operating System :: OS Independent
Requires-Python: >=3.8
Requires-Dist: torch>=2.0.0
Requires-Dist: numpy<2.0.0
Requires-Dist: tqdm
Requires-Dist: matplotlib
